{
    "type" : "FeatureCollection",
    "features" : [
        {
            "properties" : {
                "opening_hours" : "We 07:00-13:00; Sa 07:00-13:00",
                "title" : "Wochenmarkt Geestemünde",
                "location" : "Konrad-Adenauer-Platz"
            },
            "type" : "Feature",
            "geometry" : {
                "type" : "Point",
                "coordinates" : [
		    8.5915937,
		    53.5308222
                ]
            }
        },
        {
            "properties" : {
                "opening_hours" : "We 07:00-13:00; Sa 07:00-13:00",
                "title" : "Wochenmarkt Bogenstraße",
                "location" : "Bogenstraße"
            },
            "type" : "Feature",
            "geometry" : {
                "type" : "Point",
                "coordinates" : [
		    8.5741418,
                    53.5508365
                ]
            }
        },
        {
            "properties" : {
                "opening_hours" : "We 07:00-13:00; Sa 07:00-13:00",
                "title" : "Wochenmarkt Lehe",
                "location" : "Ernst-Reuter-Platz"
            },
            "type" : "Feature",
            "geometry" : {
                "type" : "Point",
                "coordinates" : [
		    8.586179,
 		    53.557772
                ]
            }
        },
        {
            "properties" : {
                "opening_hours" : "We 07:00-13:00; Sa 07:00-13:00",
                "title" : "Wochenmarkt Leherheide",
                "location" : "Hans-Böckler-Straße"
            },
            "type" : "Feature",
            "geometry" : {
                "type" : "Point",
                "coordinates" : [
		    8.6171624,
		    53.5892006
                ]
            }
        },
        {
            "properties" : {
                "opening_hours" : "Fr 10:00-17:00",
                "title" : "Wochenmarkt Wulsdorf",
                "location" : "Heinrich-Kappelmann-Straße"
            },
            "type" : "Feature",
            "geometry" : {
                "type" : "Point",
                "coordinates" : [
		    8.597187,
		    53.5056619
                ]
            }
        },
        {
            "properties" : {
                "opening_hours" : "Mo 14:00-18:00; Tu 14:00-18:00; We 14:00-18:00; Th 14:00-18:00; Fr 14:00-18:00; Sa 14:00-18:00;",
                "title" : "Markt vor der Großen Kirche",
                "location" : "Große Kirche"
            },
            "type" : "Feature",
            "geometry" : {
                "type" : "Point",
                "coordinates" : [
		    8.578986,
		    53.544242
                ]
            }
        }
    ],
    "metadata" : {
        "data_source" : {
            "url" : "http://www.bremerhaven.de/meer-erleben/shopping-gastronomie/wochenmaerkte-in-bremerhaven.95222.html",
            "title" : "Stadt Bremerhaven"
        },
        "map_initialization" : {
            "zoom_level" : 11,
            "coordinates" : [
		8.578039,
		53.541939
            ]
        }
    }
}
